hpproj/__init__.py
hpproj/cutsky.py
hpproj/decorator.py
hpproj/hp_helper.py
hpproj/parse.py
hpproj/visu.py
hpproj/wcs_helper.py
hpproj-0.9.2.dist-info/LICENSE
hpproj-0.9.2.dist-info/LICENSE_short
hpproj-0.9.2.dist-info/METADATA
hpproj-0.9.2.dist-info/WHEEL
hpproj-0.9.2.dist-info/entry_points.txt
hpproj-0.9.2.dist-info/top_level.txt
hpproj-0.9.2.dist-info/RECORD
