Metadata-Version: 2.1
Name: hpproj
Version: 0.9.2
Summary: Projection of Healpix maps onto a planar grid
Home-page: https://git.ias.u-psud.fr/abeelen/hpproj
Author: Alexandre Beelen, Marian Douspis
Author-email: alexandre.beelen@ias.u-psud.fr
License: LGPL-3.0+
Download-URL: https://git.ias.u-psud.fr/abeelen/hpproj/repository/archive.tar.gz?0.9.2
Platform: UNKNOWN
Classifier: Programming Language :: Python :: 2.7
Classifier: Programming Language :: Python :: 3.5
Classifier: Topic :: Scientific/Engineering :: Astronomy
Classifier: Intended Audience :: Science/Research
Classifier: License :: OSI Approved :: GNU Lesser General Public License v3 or later (LGPLv3+)
Requires-Dist: numpy (>=1.11)
Requires-Dist: matplotlib (>=2.0)
Requires-Dist: astropy (>=1.2)
Requires-Dist: healpy (>=1.9)
Requires-Dist: photutils (>=0.2)
